nikola_plugin_manager/__init__.py
nikola_plugin_manager/action_base.py
nikola_plugin_manager/all_of_your_base.py
nikola_plugin_manager/exceptions.py
nikola_plugin_manager/plugin_base.py
nikola_plugin_manager/plugin_manager.py
nikola_plugin_manager/profile_validator.py
nikola_plugin_manager/drivers/__init__.py
nikola_plugin_manager/notifications/__init__.py
nikola_plugin_manager-0.0.2.dist-info/METADATA
nikola_plugin_manager-0.0.2.dist-info/WHEEL
nikola_plugin_manager-0.0.2.dist-info/top_level.txt
nikola_plugin_manager-0.0.2.dist-info/RECORD
